spiegelib/__init__.py
spiegelib/core/__init__.py
spiegelib/core/audio_buffer.py
spiegelib/core/dataset_generator.py
spiegelib/core/sound_match.py
spiegelib/core/utils.py
spiegelib/estimator/__init__.py
spiegelib/estimator/basic_ga.py
spiegelib/estimator/conv6.py
spiegelib/estimator/estimator_base.py
spiegelib/estimator/highway_layer.py
spiegelib/estimator/hwy_blstm.py
spiegelib/estimator/lstm.py
spiegelib/estimator/mlp.py
spiegelib/estimator/nsga3.py
spiegelib/estimator/tf_epoch_logger.py
spiegelib/estimator/tf_estimator_base.py
spiegelib/evaluation/__init__.py
spiegelib/evaluation/evaluation_base.py
spiegelib/evaluation/mfcc_eval.py
spiegelib/evaluation/subjective.py
spiegelib/evaluation/beaqlejs/__init__.py
spiegelib/evaluation/beaqlejs/ajax-loader.gif
spiegelib/evaluation/beaqlejs/beaqle.js
spiegelib/evaluation/beaqlejs/config_mushra.json
spiegelib/evaluation/beaqlejs/index.html
spiegelib/evaluation/beaqlejs/jquery-ui-1.8.18.custom.css
spiegelib/evaluation/beaqlejs/jquery-ui.custom.min.js
spiegelib/evaluation/beaqlejs/jquery.js
spiegelib/evaluation/beaqlejs/styles.css
spiegelib/evaluation/beaqlejs/img/__init__.py
spiegelib/evaluation/beaqlejs/img/ajax-loader16.gif
spiegelib/evaluation/beaqlejs/img/scale.png
spiegelib/evaluation/beaqlejs/img/scale_abs.png
spiegelib/evaluation/beaqlejs/img/scale_abs_background.png
spiegelib/evaluation/beaqlejs/img/ui-bg_flat_0_aaaaaa_40x100.png
spiegelib/evaluation/beaqlejs/img/ui-bg_flat_75_ffffff_40x100.png
spiegelib/evaluation/beaqlejs/img/ui-bg_glass_55_fbf9ee_1x400.png
spiegelib/evaluation/beaqlejs/img/ui-bg_glass_65_ffffff_1x400.png
spiegelib/evaluation/beaqlejs/img/ui-bg_glass_75_dadada_1x400.png
spiegelib/evaluation/beaqlejs/img/ui-bg_glass_75_e6e6e6_1x400.png
spiegelib/evaluation/beaqlejs/img/ui-bg_glass_95_fef1ec_1x400.png
spiegelib/evaluation/beaqlejs/img/ui-bg_highlight-soft_75_cccccc_1x100.png
spiegelib/evaluation/beaqlejs/img/ui-icons_222222_256x240.png
spiegelib/evaluation/beaqlejs/img/ui-icons_2e83ff_256x240.png
spiegelib-0.0.4.dist-info/LICENSE
spiegelib-0.0.4.dist-info/METADATA
spiegelib-0.0.4.dist-info/WHEEL
spiegelib-0.0.4.dist-info/top_level.txt
spiegelib-0.0.4.dist-info/RECORD
