Metadata-Version: 2.1
Name: spiegelib
Version: 0.0.4
Summary: Synthesizer Programming with Intelligent Exploration, Generation, and Evaluation Library
Home-page: https://github.com/spiegelib/spiegelib
Author: Jordie Shier
Author-email: jordieshier@gmail.com
License: MIT
Platform: UNKNOWN
Requires-Python: >=3.6
Requires-Dist: numpy
Requires-Dist: librosa
Requires-Dist: tqdm
Requires-Dist: matplotlib
Requires-Dist: tensorflow
Requires-Dist: deap
Requires-Dist: numba (==0.48)
Requires-Dist: scipy (==1.4.1)
Requires-Dist: importlib-resources ; python_version < "3.7"
Provides-Extra: dev
Requires-Dist: sphinx ; extra == 'dev'
Requires-Dist: sphinx-rtd-theme ; extra == 'dev'
Requires-Dist: ipython ; extra == 'dev'
Requires-Dist: pytest ; extra == 'dev'
Requires-Dist: pytest-datadir ; extra == 'dev'
Requires-Dist: pytest-mpl ; extra == 'dev'
Requires-Dist: tox ; extra == 'dev'
Requires-Dist: twine ; extra == 'dev'
